daw/__init__.py
daw/api.py
daw/errors.py
daw/query.py
daw-0.2.dist-info/METADATA
daw-0.2.dist-info/WHEEL
daw-0.2.dist-info/top_level.txt
daw-0.2.dist-info/RECORD
